turtledov/__init__.py
turtledov/turtledov.py
turtledov-0.1.4.dist-info/LICENSE
turtledov-0.1.4.dist-info/METADATA
turtledov-0.1.4.dist-info/WHEEL
turtledov-0.1.4.dist-info/top_level.txt
turtledov-0.1.4.dist-info/RECORD
