Metadata-Version: 2.1
Name: turtledov
Version: 0.1.4
Summary: Learn Python the creative way
Home-page: https://github.com/HirushaPramuditha/turtledov
Author: Hirusha Pramuditha
Author-email: hirushapramuditha26@gmail.com
License: UNKNOWN
Platform: UNKNOWN
Classifier: Programming Language :: Python :: 3
Classifier: License :: OSI Approved :: MIT License
Classifier: Operating System :: OS Independent
Requires-Python: >=3.6
